uselessfacts_python/__init__.py
uselessfacts_python/main.py
uselessfacts_python-0.1.1.dist-info/METADATA
uselessfacts_python-0.1.1.dist-info/WHEEL
uselessfacts_python-0.1.1.dist-info/top_level.txt
uselessfacts_python-0.1.1.dist-info/RECORD
